tilecycles/Buch.py
tilecycles/Dipole.py
tilecycles/Rahman.py
tilecycles/__init__.py
tilecycles-0.2.6.dist-info/LICENSE
tilecycles-0.2.6.dist-info/METADATA
tilecycles-0.2.6.dist-info/WHEEL
tilecycles-0.2.6.dist-info/RECORD
