Metadata-Version: 2.1
Name: tilecycles
Version: 0.2.6
Summary: 
License: MIT
Author: vitroid
Author-email: vitroid@gmail.com
Requires-Python: >=3.9
Classifier: License :: OSI Approved :: MIT License
Classifier: Programming Language :: Python :: 3
Classifier: Programming Language :: Python :: 3.9
Classifier: Programming Language :: Python :: 3.10
Classifier: Programming Language :: Python :: 3.11
Classifier: Programming Language :: Python :: 3.12
Requires-Dist: networkx (>=2.0.dev20160901144005)
Requires-Dist: numpy (>=1.9,<2.0)
